xtensors/__init__.py
xtensors/version.py
xtensors/base/__init__.py
xtensors/base/_arg.py
xtensors/base/_args.py
xtensors/base/_binary_op.py
xtensors/base/_coords.py
xtensors/base/_misc.py
xtensors/base/_reduc.py
xtensors/base/_reduc_2to1.py
xtensors/base/_ufuncs.py
xtensors/functionals/__init__.py
xtensors/functionals/base.py
xtensors/functionals/reductions.py
xtensors/learn/__init__.py
xtensors/learn/confmat.py
xtensors/numpy/__init__.py
xtensors/numpy/_args.py
xtensors/numpy/_np.py
xtensors/tensor/__init__.py
xtensors/tensor/_base.py
xtensors/tensor/_decors.py
xtensors/tensor/_slice.py
xtensors/tensor/basic_utils/__init__.py
xtensors/tensor/basic_utils/_axes.py
xtensors/tensor/basic_utils/_base.py
xtensors/tensor/basic_utils/_coords.py
xtensors/tensor/basic_utils/_dims.py
xtensors/tensor/basic_utils/_generalize.py
xtensors/tensor/basic_utils/_misc.py
xtensors/tensor/broadcast/__init__.py
xtensors/tensor/broadcast/_broadcast.py
xtensors/tensor/broadcast/_dimcast.py
xtensors/tensor/broadcast/_template.py
xtensors/tensor/broadcast/_types.py
xtensors/tensor/typing/__init__.py
xtensors/tensor/typing/_typing.py
xtensors-1.0.5.dist-info/LICENSE
xtensors-1.0.5.dist-info/METADATA
xtensors-1.0.5.dist-info/WHEEL
xtensors-1.0.5.dist-info/top_level.txt
xtensors-1.0.5.dist-info/RECORD
