Metadata-Version: 2.1
Name: xtensors
Version: 1.0.5
Summary: ND named tensor utilities
Home-page: https://github.com/michael-960/xtensor
Author: Michael Wang
Author-email: mike.wang96029@gmail.com
Project-URL: Bug Tracker, https://github.com/michael-960/xtensor/issues
Classifier: Programming Language :: Python :: 3
Classifier: License :: OSI Approved :: MIT License
Classifier: Operating System :: OS Independent
Requires-Python: >=3.8
License-File: LICENSE
Requires-Dist: numpy (>=1.23)
Requires-Dist: scipy (>=1.9)
